rbpodo/__init__.py
rbpodo/_rbpodo.cpython-311-x86_64-linux-gnu.so
rbpodo/_rbpodo/__init__.pyi
rbpodo/_rbpodo/asyncio.pyi
rbpodo-0.16.9.dist-info/METADATA
rbpodo-0.16.9.dist-info/WHEEL
rbpodo-0.16.9.dist-info/RECORD
rbpodo-0.16.9.dist-info/licenses/LICENSE
