Metadata-Version: 2.2
Name: rbpodo
Version: 0.16.9
Summary: A client library for Rainbow Robotics' cobot RB-Series
Author-Email: Keunjun Choi <keunjun.choi@rainbow-robotics.com>
License:                                  Apache License
Classifier: Programming Language :: Python :: 3 :: Only
Classifier: Programming Language :: Python :: 3.8
Classifier: Programming Language :: Python :: 3.9
Classifier: Programming Language :: Python :: 3.10
Classifier: Programming Language :: Python :: 3.11
Classifier: Programming Language :: Python :: 3.12
Requires-Python: >=3.8
Requires-Dist: pybind11<3.0.0rc1,>=2.11.1; python_version < "3.8"
Requires-Dist: numpy<2.0,>=1.19; python_version < "3.8"
Requires-Dist: pybind11>=3.0.0rc1; python_version >= "3.8"
Requires-Dist: numpy>=1.19; python_version >= "3.8"
Provides-Extra: test
Requires-Dist: pytest; extra == "test"
